{
  "parent": "quest_giver:quest_0014_01",
  "reputation": 10,
  "icon": "minecraft:emerald",
  "start": {
    "title": {
      "text": "Готово!"
    },
    "description": {
      "text": "А? Ты победил Хранителя Ока до того, как я дал тебе карту? Хм... Тогда покажи мне то самое Око, которое осталось от Хранителя. На самом деле, брось его на землю и подбери снова... Просто не спрашивай!"
    }
  },
  "complete": {
    "title": {
      "text": "Конец Путешествия"
    },
    "description": {
      "text": "У меня больше нет для тебя информации, мой друг. Следуй своему призванию."
    }
  },
  "tasks": [
    {
      "item": {
        "item": "endrem:corrupted_eye"
      },
      "id": "quest_giver:item_pickup",
      "times": 1
    }
  ]
}